dcp_diag/__init__.py
dcp_diag/version.py
dcp_diag/api_agents/__init__.py
dcp_diag/api_agents/data_store_agent.py
dcp_diag/api_agents/hateoas_agent.py
dcp_diag/api_agents/ingest_api_agent.py
dcp_diag/api_agents/ingest_auth_agent.py
dcp_diag/api_agents/ingest_entities.py
dcp_diag/api_agents/ingest_ui_agent.py
dcp_diag/component_agents/__init__.py
dcp_diag/component_agents/analysis_agent.py
dcp_diag/component_agents/azul_agent.py
dcp_diag/component_agents/data_store_agent.py
dcp_diag/component_agents/hateoas_agent.py
dcp_diag/component_agents/ingest_api_agent.py
dcp_diag/component_agents/ingest_auth_agent.py
dcp_diag/component_agents/ingest_entities.py
dcp_diag/component_agents/ingest_ui_agent.py
dcp_diag/component_agents/upload_entities.py
dcp_diag/component_entities/__init__.py
dcp_diag/component_entities/analysis_entities.py
dcp_diag/component_entities/ingest_entities.py
dcp_diag/component_entities/upload_entities.py
dcp_diag/finders/__init__.py
dcp_diag/finders/analysis_finder.py
dcp_diag/finders/finder.py
dcp_diag/finders/ingest_finder.py
dcp_diag/finders/upload_finder.py
dcp_diag-1.3.0.data/scripts/analyze-submission
dcp_diag-1.3.0.data/scripts/dcpdig
dcp_diag-1.3.0.dist-info/LICENSE
dcp_diag-1.3.0.dist-info/METADATA
dcp_diag-1.3.0.dist-info/WHEEL
dcp_diag-1.3.0.dist-info/top_level.txt
dcp_diag-1.3.0.dist-info/RECORD
