Metadata-Version: 2.1
Name: dcp-diag
Version: 1.3.0
Summary: Data Coordination Platform diagnostic library and tools.
Home-page: https://github.com/HumanCellAtlas/dcp-diag
Author: Sam Pierson
Author-email: spierson@chanzuckerberg.com
License: MIT
Platform: MacOS X
Platform: Posix
Classifier: Intended Audience :: Developers
Classifier: License :: OSI Approved :: MIT License
Classifier: Operating System :: MacOS :: MacOS X
Classifier: Operating System :: POSIX
Classifier: Programming Language :: Python :: 3.6
Requires-Dist: boto3 (>=1.7.13)
Requires-Dist: cromwell-tools (>=v1.1.0)
Requires-Dist: hca
Requires-Dist: psycopg2-binary
Requires-Dist: requests (>=2.20.0)
Requires-Dist: sqlalchemy
Requires-Dist: termcolor
Requires-Dist: dcplib (<4,>=3.2.1)
